crappytext/__init__.py
crappytext/__main__.py
crappytext/core.py
crappytext-0.1.1.dist-info/licenses/LICENSE
crappytext-0.1.1.dist-info/METADATA
crappytext-0.1.1.dist-info/WHEEL
crappytext-0.1.1.dist-info/entry_points.txt
crappytext-0.1.1.dist-info/top_level.txt
crappytext-0.1.1.dist-info/RECORD
