Metadata-Version: 2.4
Name: crappytext
Version: 0.1.1
Summary: The world's crappiest text editor
Author: jacklak
License: MIT License
Requires-Python: >=3.10
License-File: LICENSE
Requires-Dist: prompt_toolkit>=3.0.0
Dynamic: license-file
